<?xml version="1.0" encoding="utf-8"?>
<!--

    Copyright (C) 2009-2018 SAP SE or an SAP affiliate company. All rights reserved.

-->
<edmx:Edmx xmlns:edmx="http://docs.oasis-open.org/odata/ns/edmx" Version="4.0">
	<edmx:Reference Uri="/sap/bc/ui5_ui5/ui2/ushell/resources/sap/ushell/components/factsheet/vocabularies/UI.xml">
		<edmx:Include Alias="UI" Namespace="com.sap.vocabularies.UI.v1"/>
	</edmx:Reference>
	<edmx:Reference Uri="/sap/opu/odata/sap/O2C_CI_BILLPLAN_MANAGE_SRV/$metadata">
		<edmx:Include Alias="O2C_CI_BILLPLAN_MANAGE_SRV" Namespace="O2C_CI_BILLPLAN_MANAGE_SRV"/>
	</edmx:Reference>
	<edmx:Reference Uri="http://docs.oasis-open.org/odata/odata-data-aggregation-ext/v4.0/cs02/vocabularies/Org.OData.Aggregation.V1.xml">
		<edmx:Include Alias="Aggregation" Namespace="Org.OData.Aggregation.V1"/>
	</edmx:Reference>
	<edmx:Reference Uri="http://docs.oasis-open.org/odata/odata/v4.0/errata03/os/complete/vocabularies/Org.OData.Capabilities.V1.xml">
		<edmx:Include Alias="Capabilities" Namespace="Org.OData.Capabilities.V1"/>
	</edmx:Reference>
	<edmx:Reference Uri="https://wiki.scn.sap.com/wiki/download/attachments/448470974/Common.xml?api=v2">
		<edmx:Include Alias="Common" Namespace="com.sap.vocabularies.Common.v1"/>
	</edmx:Reference>
	<edmx:Reference Uri="https://wiki.scn.sap.com/wiki/download/attachments/448470971/Communication.xml?api=v2">
		<edmx:Include Alias="vCard" Namespace="com.sap.vocabularies.Communication.v1"/>
	</edmx:Reference>
	<edmx:Reference Uri="/sap/opu/odata/IWFND/CATALOGSERVICE;v=2/Vocabularies(TechnicalName='%2FIWBEP%2FVOC_COMMUNICATION',Version='0001',SAP__Origin='LOCAL')/$value">
		<edmx:Include Namespace="com.sap.vocabularies.Communication.v1" Alias="Communication"/>
	</edmx:Reference>
	<edmx:Reference Uri="http://docs.oasis-open.org/odata/odata/v4.0/errata03/os/complete/vocabularies/Org.OData.Core.V1.xml">
		<edmx:Include Alias="Core" Namespace="Org.OData.Core.V1"/>
	</edmx:Reference>
	<edmx:Reference Uri="http://docs.oasis-open.org/odata/odata/v4.0/errata03/os/complete/vocabularies/Org.OData.Measures.V1.xml">
		<edmx:Include Alias="CQP" Namespace="Org.OData.Measures.V1"/>
	</edmx:Reference>
	<edmx:DataServices>
		<Schema xmlns="http://docs.oasis-open.org/odata/ns/edm" Namespace="cus.o2c.billplan.manage.s1.O2C_CI_BILLPLAN_MANAGE_SRV">
			<!--===============================================================================
                Entity Type from chosen collection 
                ================================================================================-->
			<Annotations Target="O2C_CI_BILLPLAN_MANAGE_SRV.C_CABillgPlnType">
				<Annotation Term="UI.HeaderFacets">
					<Collection>
						<Record Type="UI.ReferenceFacet">
							<PropertyValue Property="Address" String="Address"/>
							<PropertyValue Property="Target" AnnotationPath="@Communication.Address" />
						</Record>
						<Record Type="UI.ReferenceFacet">
							<PropertyValue Property="Target" AnnotationPath="@UI.FieldGroup#HeaderColumnCenter"/>
						</Record>
						<Record Type="UI.ReferenceFacet">
							<PropertyValue Property="Target" AnnotationPath="@UI.FieldGroup#HeaderColumnRight"/>
						</Record>
						<!--<Record Type="UI.ReferenceFacet">-->
						<!--	<PropertyValue AnnotationPath="@UI.DataPoint#CAAmountInTransactionCurrency" Property="Target"/>-->
						<!--</Record>-->
						<!--<Record Type="UI.ReferenceFacet">-->
						<!--	<PropertyValue AnnotationPath="@UI.DataPoint#CABillgReqTotalAmount" Property="Target"/>-->
						<!--</Record>-->
					</Collection>
				</Annotation>
				<Annotation Term="UI.Facets">
					<Collection>
						<Record Type="UI.CollectionFacet">
							<PropertyValue Property="ID" String="GeneralInformation"/>
							<PropertyValue Property="Label" String="{@i18n&gt;@GeneralInfoFacetLabel}"/>
							<PropertyValue Property="Facets">
								<Collection>
									<Record Type="UI.ReferenceFacet">
										<PropertyValue Property="Label" String="{@i18n&gt;@BASIC}"/>
										<PropertyValue Property="Target" AnnotationPath="@UI.FieldGroup#GeneralInfoBasic"/>
									</Record>
									<Record Type="UI.ReferenceFacet">
										<PropertyValue Property="Label" String="{@i18n&gt;@CHANGES}"/>
										<PropertyValue Property="Target" AnnotationPath="@UI.FieldGroup#GeneralInfoChanges"/>
									</Record>
									<Record Type="UI.ReferenceFacet">
										<PropertyValue Property="Label" String="{@i18n&gt;@DESCRIPTION}"/>
										<PropertyValue Property="Target" AnnotationPath="@UI.FieldGroup#GeneralInfoText"/>
									</Record>
								</Collection>
							</PropertyValue>
						</Record>
						<Record Type="UI.ReferenceFacet">
							<PropertyValue Property="ID" String="Items"/>
							<PropertyValue Property="Label" String="{@i18n&gt;@PLAN_ITEMS}"/>
							<PropertyValue Property="Target" AnnotationPath="to_CABillgPlnItem/@UI.LineItem" />
						</Record>
						<!--Record Type="UI.ReferenceFacet">
							<PropertyValue Property="Label" String="Exceptions"/>
							<PropertyValue Property="ID" String="Exceptions"/>
							<PropertyValue Property="Target" AnnotationPath="to_CABillgPlnItem/@UI.LineItem" />
						</Record-->
						<Record Type="UI.ReferenceFacet">
							<PropertyValue Property="Label" String="{@i18n&gt;@REQUEST_HISTORY}"/>
							<PropertyValue Property="ID" String="BillableItems"/>
							<PropertyValue Property="Target" AnnotationPath="to_CABillgPlnBllbleItm/@UI.LineItem" />
						</Record>
						<Record Type="UI.ReferenceFacet">
							<PropertyValue Property="Label" String="{@i18n&gt;@REFERENCE}"/> 
							<PropertyValue Property="ID" String="Reference"/>
							<PropertyValue Property="Target" AnnotationPath="to_CABillgPlnRef/@UI.LineItem" />
						</Record>
					</Collection>
				</Annotation>
			</Annotations>
			<!--===============================================================================
                Entity Type from chosen navigation property
                ================================================================================-->
			<Annotations Target="O2C_CI_BILLPLAN_MANAGE_SRV.C_CABillgPlnItemType">
			    
				<Annotation Term="UI.Facets">
					<Collection>
						<Record Type="UI.CollectionFacet">
							<PropertyValue Property="ID" String="GeneralInformation"/>
							<PropertyValue Property="Label" String="{@i18n&gt;@GeneralInfoFacetLabel}"/>
							<PropertyValue Property="Facets">
								<Collection>
									<Record Type="UI.ReferenceFacet">
										<PropertyValue Property="Label" String="{@i18n&gt;@GeneralInfoFacetLabel}"/>
										<PropertyValue Property="Target" AnnotationPath="@UI.Identification"/>
									</Record>
								</Collection>
							</PropertyValue>
						</Record>
					</Collection>
				</Annotation>
				
				<!--<Annotation Term="com.sap.vocabularies.Common.v1.SideEffects" Qualifier="RecurringItemChange">-->
    <!--                <Record>-->
    <!--                    <PropertyValue Property="SourceProperties">-->
    <!--                        <Collection>-->
    <!--                            <PropertyPath>CABillgPlnItmType</PropertyPath>-->
    <!--                        </Collection>-->
    <!--                    </PropertyValue>-->
    <!--                    <PropertyValue Property="EffectTypes" EnumMember="ValueChange"/>-->
    <!--                    <PropertyValue Property="TargetProperties">-->
    <!--                        <Collection>-->
    <!--                            <PropertyPath>CABillgPlnItemRecurring</PropertyPath>-->
    <!--                        </Collection>-->
    <!--                    </PropertyValue>-->
    <!--                </Record>-->
    <!--            </Annotation>-->
			</Annotations>
		</Schema>
	</edmx:DataServices>
</edmx:Edmx>